[
    {
        "type": "message",
        "user": "U1NLH1CP8",
        "text": "Is this hill you speak of well lit?",
        "ts": "1477946134.000005",
        "reactions": [
            {
                "name": "flashlight",
                "users": [
                    "U1KRE5NKZ"
                ],
                "count": 1
            }
        ]
    },
    {
        "type": "message",
        "user": "U1KRZT11T",
        "text": "That's a good point. I am not really sure, potentially not. But we can make any boring run lit",
        "ts": "1477956873.000006"
    },
    {
        "type": "message",
        "user": "U1KRE5NKZ",
        "text": "Should we wait to do that one until we turn the clocks back then?",
        "ts": "1477959602.000007"
    },
    {
        "type": "message",
        "user": "U1KRZT11T",
        "text": "Sure do you guys still want to meet in the morning or should we shoot for afternoon running",
        "ts": "1477959656.000008",
        "reactions": [
            {
                "name": "sun_with_face",
                "users": [
                    "U1N43E3E0"
                ],
                "count": 1
            }
        ]
    },
    {
        "type": "message",
        "user": "U1L5GU954",
        "text": "Sorry guys, I'm out tomorrow. Starting my taper!",
        "ts": "1477960392.000009",
        "reactions": [
            {
                "name": "pizza",
                "users": [
                    "U1KRE5NKZ",
                    "U1KRZT11T"
                ],
                "count": 2
            },
            {
                "name": "runner",
                "users": [
                    "U1KRE5NKZ"
                ],
                "count": 1
            },
            {
                "name": "trophy",
                "users": [
                    "U1NLH1CP8"
                ],
                "count": 1
            },
            {
                "name": "zzz",
                "users": [
                    "U1NLH1CP8"
                ],
                "count": 1
            }
        ]
    },
    {
        "type": "message",
        "user": "U1KRE5NKZ",
        "text": "Would be ok with morning if that still works? Centennial at least has some lights\/sidewalks",
        "ts": "1477960636.000010"
    },
    {
        "type": "message",
        "user": "U1KRZT11T",
        "text": "Ok meet at the institute ",
        "ts": "1477962074.000011",
        "reactions": [
            {
                "name": "+1",
                "users": [
                    "U1NLH1CP8",
                    "U1KT5F4SZ",
                    "U1KRE5NKZ"
                ],
                "count": 3
            }
        ]
    }
]