[
    {
        "type": "message",
        "user": "U1L0V1X61",
        "text": "Restorative Yoga at 5:15pm - anyone wanting to join in?",
        "ts": "1469466713.000002"
    },
    {
        "type": "message",
        "user": "U1LMHQY9E",
        "text": "If we get to a good stopping point in our project I could be in",
        "ts": "1469470079.000003"
    },
    {
        "type": "message",
        "user": "U1KR9BP0E",
        "text": "I'm going to cycling instead today <@U1L0V1X61>",
        "ts": "1469471783.000004"
    }
]