[
    {
        "type": "message",
        "user": "U1KS4UE2F",
        "text": "does anyone want to uber to the place with me ~12pm?",
        "ts": "1472303485.000002",
        "reactions": [
            {
                "name": "blue_car",
                "users": [
                    "U1L5GU954"
                ],
                "count": 1
            }
        ]
    },
    {
        "type": "message",
        "user": "U1L6YQUSU",
        "text": "Don't forget your IDs today!!!!",
        "ts": "1472310081.000003"
    },
    {
        "type": "message",
        "user": "U1L6YQUSU",
        "text": "Also I'm running a little behind.  Should be there by 12:45.  I think someone from the tour should be there already by 12:30.",
        "ts": "1472314114.000004"
    },
    {
        "type": "message",
        "user": "U1KRTHAQZ",
        "text": "I'm here. They're still getting set up",
        "ts": "1472314503.000005"
    },
    {
        "type": "message",
        "user": "U1L7E8GSU",
        "text": "Running a little late too but on my way! ",
        "ts": "1472315048.000006"
    },
    {
        "user": "U1L95JP1S",
        "text": "<@U1L95JP1S|mattkelk> has left the channel",
        "type": "message",
        "subtype": "channel_leave",
        "ts": "1472342699.000002"
    }
]