[
    {
        "type": "message",
        "user": "U1L1D4WG7",
        "text": "A few of us were talking about length of variables in the library yesterday, and I thought the concatenation discussion was worth looking up... here is what I found... CATS, CATX, CAT all make the variable length=200. However concatenating with the || option (e.g. CatOper = \"1\"||\"2\";) assigns a length that is the total of the things concatenated, 2 in this case.",
        "edited": {
            "user": "U1L1D4WG7",
            "ts": "1470924135.000000"
        },
        "ts": "1470924116.000125",
        "reactions": [
            {
                "name": "+1",
                "users": [
                    "U1L6YQUSU",
                    "U1L9DD1NY",
                    "U1KSL7C10"
                ],
                "count": 3
            }
        ]
    },
    {
        "type": "message",
        "user": "U1L6YQUSU",
        "text": "I assume CATT is the same as the other ones, <@U1L1D4WG7> ?",
        "ts": "1470925263.000127"
    },
    {
        "type": "message",
        "user": "U1L1D4WG7",
        "text": "Yes,  just checked that one too. CATT length is 200.",
        "ts": "1470925363.000128"
    },
    {
        "type": "message",
        "user": "U1L6WB44A",
        "text": "This is the paper Joy is talking about that explains merging: <http:\/\/www2.sas.com\/proceedings\/sugi22\/ADVTUTOR\/PAPER39.PDF>",
        "ts": "1470927014.000129",
        "reactions": [
            {
                "name": "+1",
                "users": [
                    "U1KRZT11T",
                    "U1LBRCSEA",
                    "U1L9DD1NY"
                ],
                "count": 3
            }
        ]
    },
    {
        "type": "message",
        "user": "U1NUU2U9E",
        "text": "tried to test the code of answer C in SAS and it gives an error on OPTION... wrong answer?",
        "ts": "1470929180.000131"
    },
    {
        "type": "message",
        "user": "U1L6YQUSU",
        "text": "Dlm goes in the infile statement without the word \"option\"",
        "ts": "1470929238.000132"
    },
    {
        "type": "message",
        "user": "U1L6YQUSU",
        "text": "So C is the closest answer, but I don't think any of them are correct ",
        "ts": "1470929266.000133",
        "reactions": [
            {
                "name": "+1",
                "users": [
                    "U1L1D4WG7"
                ],
                "count": 1
            }
        ]
    },
    {
        "type": "message",
        "user": "U1L0V1X61",
        "text": "Perhaps you can have dlm as a global option?",
        "ts": "1470929293.000134"
    },
    {
        "type": "message",
        "user": "U1L0V1X61",
        "text": "So B would be the closest, if that is the case",
        "ts": "1470929324.000135"
    },
    {
        "type": "message",
        "user": "U1L6YQUSU",
        "text": "I don't think it's a global option ",
        "ts": "1470929444.000136"
    },
    {
        "type": "message",
        "user": "U1L0V1X61",
        "text": "nope - just tried that in SAS... you cannot use dlm as a global",
        "ts": "1470929446.000137"
    },
    {
        "type": "message",
        "user": "U1L0V1X61",
        "text": "sorry - no idea on this one...",
        "ts": "1470929600.000138"
    },
    {
        "type": "message",
        "user": "U1LBRCSEA",
        "text": "must be a wrong answer",
        "ts": "1470929620.000139"
    },
    {
        "type": "message",
        "user": "U1L6YQUSU",
        "text": "I agree with <@U1LBRCSEA> ",
        "ts": "1470929637.000140"
    },
    {
        "type": "message",
        "user": "U1NUU2U9E",
        "text": "thanks! i thought i was missing something...",
        "ts": "1470929685.000141"
    },
    {
        "user": "U1PNNRVGF",
        "text": "<@U1PNNRVGF|basoren2> has joined the channel",
        "type": "message",
        "subtype": "channel_join",
        "ts": "1470933139.000142"
    },
    {
        "type": "message",
        "user": "U1KQYG6SJ",
        "text": "Are we able to move back and forth between questions on the exam?",
        "ts": "1470935095.000143"
    },
    {
        "type": "message",
        "user": "U1KRHCR7T",
        "text": "I think you can, yeah",
        "ts": "1470935128.000144"
    },
    {
        "type": "message",
        "user": "U1L6YQUSU",
        "text": "You can <@U1KQYG6SJ> ",
        "ts": "1470935140.000145"
    },
    {
        "type": "message",
        "user": "U1KQYG6SJ",
        "text": "John, what would we do without you?",
        "ts": "1470935436.000146"
    },
    {
        "type": "message",
        "user": "U1L6YQUSU",
        "text": "I don't even want to think about that. ",
        "ts": "1470935450.000147",
        "reactions": [
            {
                "name": "joy",
                "users": [
                    "U1KQYG6SJ",
                    "U1L9DD1NY"
                ],
                "count": 2
            }
        ]
    },
    {
        "type": "message",
        "user": "U1KRNH021",
        "text": "Can anyone help me out in understanding how the third when statement is also met. There is no month so it is only the second when statement right. ",
        "ts": "1470935576.000149"
    },
    {
        "type": "message",
        "user": "U1L6YQUSU",
        "text": "I'm not sure I understand your question.  ",
        "ts": "1470935659.000150"
    },
    {
        "type": "message",
        "user": "U1KQYG6SJ",
        "text": "I think I do... the when statement doesn't have to be exhaustively true",
        "ts": "1470935701.000151"
    },
    {
        "type": "message",
        "user": "U1KQYG6SJ",
        "text": "anything that satisfies the second statement (or even the first) will also satisfy the third",
        "ts": "1470935719.000152"
    },
    {
        "type": "message",
        "user": "U1KQYG6SJ",
        "text": "since it has to be \"bear\" to satisfy those previous ones",
        "ts": "1470935734.000153"
    },
    {
        "type": "message",
        "user": "U1KRNH021",
        "text": "Thanks <@U1KQYG6SJ> ",
        "ts": "1470935774.000154"
    },
    {
        "type": "message",
        "user": "U1L6YQUSU",
        "text": "But it won't ever get to the 3rd one if it satisfies one of the first two.",
        "ts": "1470935851.000155",
        "reactions": [
            {
                "name": "+1::skin-tone-5",
                "users": [
                    "U1KQYG6SJ"
                ],
                "count": 1
            }
        ]
    },
    {
        "type": "message",
        "user": "U1NUU2U9E",
        "text": "I finished all the questions and quizzes and trying to take the Practice Exam on sas' website... do i need to have some type of code to get it? asks for $55 :disappointed:",
        "ts": "1470935911.000156"
    },
    {
        "type": "message",
        "user": "U1KR9BP0E",
        "text": "<@U1NUU2U9E>: did you ever do the elearnings? its the same code you need to access that",
        "ts": "1470935947.000157"
    },
    {
        "type": "message",
        "user": "U1NUU2U9E",
        "text": "yeah, i had the access to elearnings... let me see if i still do :slightly_smiling_face:",
        "ts": "1470935969.000158"
    },
    {
        "type": "message",
        "user": "U1KR9BP0E",
        "text": "once you log into the elearning section you'll see a practice test in that list",
        "ts": "1470935972.000159"
    },
    {
        "type": "message",
        "user": "U1KR9BP0E",
        "text": "that's the practice test",
        "ts": "1470935976.000160"
    },
    {
        "type": "message",
        "user": "U1NUU2U9E",
        "text": "<@U1KR9BP0E>:  thank you... i didn't see that before :flushed:",
        "ts": "1470936097.000161"
    },
    {
        "user": "U1KRSV7AN",
        "text": "<@U1KRSV7AN|jstauss> has joined the channel",
        "type": "message",
        "subtype": "channel_join",
        "ts": "1470936642.000162"
    },
    {
        "type": "message",
        "user": "U1KQYG6SJ",
        "text": "in case anyone is wondering (random thing I decided to test out), if you're replacing with substring, and specify fewer characters than needed, it pads with blanks\neg: substr(name, 1, 3) = \"ab\"; will sub \"ab \" (space at end)",
        "edited": {
            "user": "U1KQYG6SJ",
            "ts": "1470936703.000000"
        },
        "ts": "1470936661.000163"
    },
    {
        "type": "message",
        "user": "U1KRSV7AN",
        "text": "Hi all, can anyone help me with this question? It comes from one of the tests Edward sent out.\n\n29.The following SAS program is sumbitted:\n \n  data <http:\/\/WORK.INFO|WORK.INFO>;\n     infile 'DATAFILE.TXT';\n     input @1 Company $20. @25 State $2. @;\n     if State=' ' then input @30 Year;\n     else input @30 City Year; \n     input NumEmployees;\n  run;\n \nHow many raw data records are read during each iteration of the DATA step?",
        "ts": "1470936674.000164"
    },
    {
        "type": "message",
        "user": "USLACKBOT",
        "text": "Yo yo yo",
        "ts": "1470936676.000165"
    },
    {
        "type": "message",
        "user": "U1KRSV7AN",
        "text": "I could swear the answer would be 2 because of the last input statement, but it says the answer is 1. :confused:",
        "ts": "1470936699.000167"
    },
    {
        "type": "message",
        "user": "U1KQYG6SJ",
        "text": "<@U1KRSV7AN>: at the review session last week, Andrea said it should be 2",
        "ts": "1470936727.000169",
        "reactions": [
            {
                "name": "+1",
                "users": [
                    "U1L1D4WG7"
                ],
                "count": 1
            }
        ]
    },
    {
        "type": "message",
        "user": "U1KRSV7AN",
        "text": "Boom. #validated",
        "ts": "1470936738.000170"
    },
    {
        "type": "message",
        "user": "U1KRSV7AN",
        "text": "Thanks <@U1KQYG6SJ> :slightly_smiling_face:",
        "ts": "1470936749.000171"
    },
    {
        "type": "message",
        "user": "U1KQYG6SJ",
        "text": "lol",
        "ts": "1470936757.000172"
    },
    {
        "type": "message",
        "user": "U1KQYG6SJ",
        "text": "I don't think I can go back to using SAS without disdain after this test...",
        "ts": "1470937066.000173"
    },
    {
        "type": "message",
        "user": "U1KRSV7AN",
        "text": "Agreed. I thought about keeping a log of my complaints about its inconsistencies. And then I realized I'd be keeping a log. Like SAS. What have I become?",
        "ts": "1470937114.000174",
        "reactions": [
            {
                "name": "joy",
                "users": [
                    "U1KRZT11T",
                    "U1L9DD1NY",
                    "U1MPXSHN1"
                ],
                "count": 3
            }
        ]
    },
    {
        "type": "message",
        "user": "U1L1D4WG7",
        "text": "this giphy correctly captures my current state of mind while studying, and also the exasperation that Rose stated...",
        "ts": "1470937250.000176"
    },
    {
        "type": "message",
        "user": "U1KR9BP0E",
        "text": "Question. In the following question the correct answer is C - my question is why does it not include 'track' as the 'fname' of the third observation? Why does it just stop after Observation 2?\n\n31. Given the following raw data records in DATAFILE.TXT:\n \n  ----|----10---|----20---|----30\n  Kim,Basketball,Golf,Tennis\n  Bill,Football\n  Tracy,Soccer,Track \n \nThe following program is submitted:\n \n  data WORK.SPORTS_INFO;\n     length Fname Sport1-Sport3 $ 10;\n     infile 'DATAFILE.TXT' dlm=',';\n     input Fname $ Sport1 $ Sport2 $ Sport3 $;\n  run;\n \n  proc print data=WORK.SPORTS_INFO;\n  run;\n \nWhich output is correct based on the submitted program? \n\n        A.\n Obs    Fname    Sport1        Sport2    Sport3\n \n 1     Kim      Basketball    Golf      Tennis\n 2     Bill     Football\n 3     Tracy    Soccer        Track\n \n     B.\n Obs    Fname    Sport1        Sport2    Sport3\n \n 1     Kim      Basketball    Golf      Tennis\n 2     Bill     Football      Football  Football \n 3     Tracy    Soccer        Track     Track\n \n     C.\n Obs    Fname    Sport1        Sport2    Sport3\n \n 1     Kim      Basketball    Golf      Tennis\n 2     Bill     Football      Tracy     Soccer\n \n     D.\n Obs    Fname    Sport1        Sport2    Sport3\n \n 1     Kim      Basketball    Golf      Tennis\n 2     Bill     Football",
        "ts": "1470942140.000177"
    },
    {
        "type": "message",
        "user": "U1L6YQUSU",
        "text": "Once it reads in \"soccer\", it advances to the next record since there's nothing to hold it on that line.  And when it advances, it hits the end of file, so it's done.",
        "ts": "1470942290.000178"
    },
    {
        "type": "message",
        "user": "U1KR9BP0E",
        "text": "Oooohhh",
        "ts": "1470942305.000179"
    },
    {
        "type": "message",
        "user": "U1KR9BP0E",
        "text": "So if there were other lines after that line, it would read those as next observations?",
        "ts": "1470942321.000180"
    },
    {
        "type": "message",
        "user": "U1L6YQUSU",
        "text": "Yes. ",
        "ts": "1470942341.000181"
    },
    {
        "type": "message",
        "user": "U1L6YQUSU",
        "text": "Try it ",
        "ts": "1470942346.000182"
    },
    {
        "type": "message",
        "user": "U1KR9BP0E",
        "text": "Thanks John! That makes sense.",
        "ts": "1470942348.000183"
    },
    {
        "type": "message",
        "user": "U1KR9BP0E",
        "text": "I wanted to try it but I kept getting errors trying to infile it and sorta gave up",
        "ts": "1470942357.000184"
    },
    {
        "type": "message",
        "user": "U1KR9BP0E",
        "text": "That makes sense.",
        "ts": "1470942401.000185"
    },
    {
        "type": "message",
        "user": "U1KRSV7AN",
        "text": "Just to add, if the 'missover' option was included in the infile statement, this code would work as intended.",
        "ts": "1470944133.000186"
    },
    {
        "type": "message",
        "user": "U1KR9BP0E",
        "text": "Yep, thanks <@U1KRSV7AN>",
        "ts": "1470944389.000187"
    },
    {
        "type": "message",
        "user": "U1L914KNJ",
        "text": "This one is weird - apparently the default sas behavoir is something called flowover",
        "ts": "1470945401.000188"
    },
    {
        "type": "message",
        "user": "U1L6YQUSU",
        "text": "Yep.  There's also truncover and stopover ",
        "ts": "1470946456.000189"
    },
    {
        "type": "message",
        "user": "U1L6YQUSU",
        "text": "But I think the base exam only deals with missover.",
        "ts": "1470947139.000190"
    },
    {
        "type": "message",
        "user": "U1KQYG6SJ",
        "text": "I understand why a is correct, but why isn't d correct too?",
        "ts": "1470947792.000192"
    },
    {
        "type": "message",
        "user": "U1KQYG6SJ",
        "text": "is it a matter of not being able to guarantee that it would hit exactly 250?",
        "ts": "1470947859.000193"
    },
    {
        "type": "message",
        "user": "U1L914KNJ",
        "text": "Hi <@U1KQYG6SJ>, I think it's because it may never exactly =250",
        "ts": "1470948022.000194"
    },
    {
        "type": "message",
        "user": "U1KQYG6SJ",
        "text": "great, thanks Nikki",
        "ts": "1470948056.000197"
    },
    {
        "type": "message",
        "user": "U1L9DD1NY",
        "text": "Does anyone remember why B is the right answer?? I remember going over this one in class but I don't remember the reasoning ",
        "ts": "1470948600.000199"
    },
    {
        "type": "message",
        "user": "U1L6WB44A",
        "text": "The else if level=2 or 3 will always evaluate as true, so you'd never get to the else for 'high' ",
        "ts": "1470948653.000200"
    },
    {
        "type": "message",
        "user": "U1L9DD1NY",
        "text": "Why does that always evaluate as true ?",
        "ts": "1470949313.000201"
    },
    {
        "type": "message",
        "user": "U1LBRCSEA",
        "text": "My understanding based on the way Andrea described it was that the number 3 is always 3\u2026so that else if statement will always be true since 3 is always 3, aka 3 is always a true statement (unlike 3=4 or something, which is always false), and you\u2019ll never make it to the else high one",
        "ts": "1470949891.000202",
        "reactions": [
            {
                "name": "+1",
                "users": [
                    "U1KRLV1CG"
                ],
                "count": 1
            }
        ]
    },
    {
        "type": "message",
        "user": "U1LBRCSEA",
        "text": "does that make sense at all?",
        "ts": "1470949898.000203"
    },
    {
        "type": "message",
        "user": "U1KRLV1CG",
        "text": "Yes, <@U1LBRCSEA> is right",
        "ts": "1470949943.000204"
    },
    {
        "type": "message",
        "user": "U1KRLV1CG",
        "text": "If you write \"else if level=2 or level=3\" then this statement would not always be true",
        "ts": "1470949992.000205"
    },
    {
        "type": "message",
        "user": "U1KRLV1CG",
        "text": "if you write \"if 3\" without linking it to a variable, then the statement is always true",
        "ts": "1470950023.000206",
        "reactions": [
            {
                "name": "+1",
                "users": [
                    "U1LBRCSEA"
                ],
                "count": 1
            }
        ]
    },
    {
        "type": "message",
        "user": "U1KQYG6SJ",
        "text": "The question is: Select the ARRAY statement that defines the array in the following program",
        "ts": "1470950972.000208"
    },
    {
        "type": "message",
        "user": "U1KRLV1CG",
        "text": "This looks like a multidimensional array, which I think is part of the advanced certification and not part of the Base certification",
        "ts": "1470951103.000209"
    },
    {
        "type": "message",
        "user": "U1KRLV1CG",
        "text": "Can somebody confirm?",
        "ts": "1470951116.000210"
    },
    {
        "type": "message",
        "user": "U1L6YQUSU",
        "text": "Confirmed ",
        "ts": "1470952159.000211",
        "reactions": [
            {
                "name": "+1",
                "users": [
                    "U1KRLV1CG"
                ],
                "count": 1
            }
        ]
    },
    {
        "type": "message",
        "user": "U1KQYG6SJ",
        "text": "but it's in the base prep guide...",
        "ts": "1470952473.000212"
    },
    {
        "type": "message",
        "user": "U1KQYG6SJ",
        "text": ":confused:",
        "ts": "1470952475.000213"
    },
    {
        "type": "message",
        "user": "U1KQYG6SJ",
        "text": "my confusion stemmed from the fact that the answer seemed to be in the question already",
        "ts": "1470952504.000214"
    },
    {
        "type": "message",
        "user": "U1KRLV1CG",
        "text": "I think it's fair game to bother Andrea for this...",
        "ts": "1470952550.000215"
    },
    {
        "type": "message",
        "user": "U1KQYG6SJ",
        "text": "I'll post it on the blog, but Andrea is out of the country, so I don't think she's responding to questions at this point",
        "ts": "1470953089.000216"
    },
    {
        "type": "message",
        "user": "U1L6YQUSU",
        "text": "I wouldn't worry about this one ",
        "ts": "1470953135.000217",
        "reactions": [
            {
                "name": "+1",
                "users": [
                    "U1KRLV1CG",
                    "U1L7E8GSU"
                ],
                "count": 2
            }
        ]
    },
    {
        "type": "message",
        "user": "U1KRLV1CG",
        "text": "I agree with <@U1L6YQUSU>",
        "ts": "1470953505.000218"
    },
    {
        "type": "message",
        "user": "U1L9DD1NY",
        "text": "Thank you! <@U1KRLV1CG> <@U1LBRCSEA> ",
        "ts": "1470954062.000219"
    },
    {
        "type": "message",
        "user": "U1L9DD1NY",
        "text": "Anyone know why this is 40?",
        "ts": "1470954383.000220"
    },
    {
        "type": "message",
        "user": "U1KSR4JP3",
        "text": "I think when it says input age 7-8 it moves to the next line. ",
        "ts": "1470954453.000222",
        "reactions": [
            {
                "name": "+1",
                "users": [
                    "U1KRLV1CG",
                    "U1P8QBBD1",
                    "U1LBRCSEA"
                ],
                "count": 3
            }
        ]
    },
    {
        "type": "message",
        "user": "U1KR9BP0E",
        "text": " <@U1L9DD1NY> there's no trailing @ after the first input ",
        "ts": "1470954466.000223"
    },
    {
        "type": "message",
        "user": "U1KR9BP0E",
        "text": "So it goes to the next line m",
        "ts": "1470954476.000224",
        "reactions": [
            {
                "name": "+1",
                "users": [
                    "U1KRLV1CG"
                ],
                "count": 1
            }
        ]
    },
    {
        "type": "message",
        "user": "U1KRHCR7T",
        "text": "But isn't age on the John line characters 6-7 rather than 7-8?",
        "ts": "1470954654.000225"
    },
    {
        "type": "message",
        "user": "U1L1D4WG7",
        "text": "That is true. Location is wrong in the program.",
        "ts": "1470954748.000226"
    },
    {
        "type": "message",
        "user": "U1KR9BP0E",
        "text": "Yeah <@U1KRHCR7T> I think it's a mistake... no other explanation unless someone else has one?",
        "ts": "1470954829.000227",
        "reactions": [
            {
                "name": "+1",
                "users": [
                    "U1KRHCR7T",
                    "U1KRLV1CG"
                ],
                "count": 2
            }
        ]
    },
    {
        "type": "message",
        "user": "U1L9DD1NY",
        "text": "Oh okay thank you guys!",
        "ts": "1470954933.000228",
        "reactions": [
            {
                "name": "+1",
                "users": [
                    "U1KR9BP0E"
                ],
                "count": 1
            }
        ]
    },
    {
        "type": "message",
        "user": "U1KQYG6SJ",
        "text": "This is one of those ones where the comments are useful -- there are apparently 2 spaces between the names and the ages",
        "ts": "1470955582.000229"
    },
    {
        "type": "message",
        "user": "U1KR9BP0E",
        "text": "Does anyone know what the \"retain temp\" does in this program since there's no accumulating variable? (The answer is C, if you're curious)\n\n10. The SAS data set Sashelp.Prdsale contains the variables Region and Salary with 4\nobservations per Region. Sashelp.Prdsale is sorted primarily by Region and within\nRegion by Salary in descending order.\nThe following program is submitted:\ndata one;\nset sashelp.prdsale;\nretain temp;\nby region descending salary;\nif first.region then\ndo;\ntemp=salary;\noutput;\nend;\nif last.region then\ndo;\nrange=salary-temp;\noutput;\nend;\nrun;\nFor each region, what is the number of observation(s) written to the output data set?\na. 0\nb. 1\nc. 2\nd. 4",
        "ts": "1470955670.000230"
    },
    {
        "type": "message",
        "user": "U1KQYG6SJ",
        "text": "I'm guessing it's because you want to hold on to the value of temp until you hit that last value so you can find the range?",
        "ts": "1470955804.000231"
    },
    {
        "type": "message",
        "user": "U1KR9BP0E",
        "text": "What would happen if there was no retain statement? It would overwrite temp = salary when it hits the first if statement, before it moves to the second if statemnet?",
        "ts": "1470955890.000232"
    },
    {
        "type": "message",
        "user": "U1KT2JJE8",
        "text": "Temp would be missing if it weren't the first record if not retained.",
        "ts": "1470955931.000233"
    },
    {
        "type": "message",
        "user": "U1KR9BP0E",
        "text": "is retain essentially an assignment statement then, in this case? It's a new variable?",
        "ts": "1470955997.000234"
    },
    {
        "type": "message",
        "user": "U1KSYP1M5",
        "text": "Okay and just to add to that why don't you need a retain statement for range since that is also a new variable?",
        "ts": "1470956051.000235"
    },
    {
        "type": "message",
        "user": "U1KT2JJE8",
        "text": "No. It keeps the value across multiple iterations of the data step so the salary of the first region can be kept for calculation.",
        "ts": "1470956063.000236"
    },
    {
        "type": "message",
        "user": "U1L6WB44A",
        "text": "On the retain stayement and not related to the problem solution, do you not have to set what you want the accumulated variable to start at? Like 'retain temp 0;' rather than just 'retain temp' . I feel like I got an error not doing that before?",
        "ts": "1470956078.000237"
    },
    {
        "type": "message",
        "user": "U1KQYG6SJ",
        "text": "it defaults to 0 if you don't specify",
        "ts": "1470956099.000238"
    },
    {
        "type": "message",
        "user": "U1KT2JJE8",
        "text": "Range only needs to be computed and written out in the same iteration.",
        "ts": "1470956106.000239"
    },
    {
        "type": "message",
        "user": "U1KT2JJE8",
        "text": "Does it default to 0 or missing?",
        "ts": "1470956134.000240"
    },
    {
        "type": "message",
        "user": "U1KT2JJE8",
        "text": "Meaning temp",
        "ts": "1470956142.000241"
    },
    {
        "type": "message",
        "user": "U1KQYG6SJ",
        "text": "0",
        "ts": "1470956231.000242"
    },
    {
        "type": "message",
        "user": "U1L6WB44A",
        "text": "Just looked it up, SAS help says missing from what I read! See the initial value section and let me know if you agree! <http:\/\/support.sas.com\/documentation\/cdl\/en\/lrdict\/64316\/HTML\/default\/viewer.htm#a000214163.htm>",
        "ts": "1470956305.000243"
    },
    {
        "type": "message",
        "user": "U1L6WB44A",
        "text": "(Retain statement default is (?) missing if no initial value is specified to clarify what the link is about) ",
        "ts": "1470956362.000244"
    },
    {
        "type": "message",
        "user": "U1L6WB44A",
        "text": "It just doesn't affect computation in this problem",
        "ts": "1470956405.000245"
    },
    {
        "type": "message",
        "user": "U1KQYG6SJ",
        "text": "hmm... I could have sworn I looked it up and it said zero at some point, but can't dispute the documentation!",
        "ts": "1470956475.000246"
    },
    {
        "type": "message",
        "user": "U1KQYG6SJ",
        "text": "good catch",
        "ts": "1470956478.000247"
    },
    {
        "type": "message",
        "user": "U1KRTHAQZ",
        "text": "I thought it was zero as well",
        "ts": "1470956559.000248"
    },
    {
        "type": "message",
        "user": "U1KQYG6SJ",
        "text": "I swear the more I study, the _dumber_ I become",
        "ts": "1470956575.000249"
    },
    {
        "type": "message",
        "user": "U1KR9BP0E",
        "text": "Ugh why do we do this to ourselves",
        "ts": "1470956583.000250"
    },
    {
        "type": "message",
        "user": "U1KR9BP0E",
        "text": "I was smarter this morning",
        "ts": "1470956588.000251"
    },
    {
        "type": "message",
        "user": "U1KQYG6SJ",
        "text": ":joy:",
        "ts": "1470956589.000252"
    },
    {
        "type": "message",
        "user": "U1L6WB44A",
        "text": "I was less paranoid this morning :joy: ",
        "ts": "1470956603.000253"
    },
    {
        "type": "message",
        "user": "U1KQYG6SJ",
        "text": "anybody want to go see secret life of pets? :joy:",
        "ts": "1470956666.000254"
    },
    {
        "type": "message",
        "user": "U1KQYG6SJ",
        "text": "It didn't get stellar reviews, but it's an animated movie so it can't be _that_ bad",
        "ts": "1470956680.000255"
    },
    {
        "type": "message",
        "user": "U1L6WB44A",
        "text": "I can attest to that! It's not that bad! ",
        "ts": "1470956728.000256"
    },
    {
        "type": "message",
        "user": "U1KRLV1CG",
        "text": "<@U1KSYP1M5>: All new variables will be set to missing at each iteration unless there is a retain statement (see link by <@U1L6WB44A>). Temp needs the retain statement because it is part of an arithmetic calculation (see second if statement). You do not need a retain statement for range because it is not part of an arithmetic calculation. You don't care if range is set to missing at every iteration.",
        "ts": "1470956762.000257"
    },
    {
        "type": "message",
        "user": "U1KSR4JP3",
        "text": "I thought when you retain something it is assigned 0 but the initial value is missing... If that makes sense. ",
        "ts": "1470956989.000258"
    },
    {
        "type": "message",
        "user": "U1KSR4JP3",
        "text": "So <@U1L6WB44A> is right. ",
        "ts": "1470957047.000259"
    },
    {
        "type": "message",
        "user": "U1KSR4JP3",
        "text": "There is a question in one of Daniel's files: ",
        "ts": "1470957271.000260"
    },
    {
        "type": "message",
        "user": "U1KQYG6SJ",
        "text": "I think that that may be a function of the fact that we're usually using those retained variables in things like sum statements which end up doing that _(but at this point, my statements are the statements of a crazy woman)_",
        "edited": {
            "user": "U1KQYG6SJ",
            "ts": "1470957348.000000"
        },
        "ts": "1470957278.000261",
        "reactions": [
            {
                "name": "raised_hands",
                "users": [
                    "U1KSR4JP3"
                ],
                "count": 1
            }
        ]
    },
    {
        "type": "message",
        "user": "U1KQYG6SJ",
        "text": "I think for the rest of the night, I'm just going to lurk and see what questions come up :zipper_mouth_face:",
        "ts": "1470957417.000267"
    },
    {
        "type": "message",
        "user": "U1KR9BP0E",
        "text": "<@U1KQYG6SJ>: I will support your continued learning by asking several questions... haha",
        "ts": "1470957460.000268",
        "reactions": [
            {
                "name": "joy",
                "users": [
                    "U1KQYG6SJ",
                    "U1KRLV1CG"
                ],
                "count": 2
            }
        ]
    },
    {
        "type": "message",
        "user": "U1KSYP1M5",
        "text": "<@U1KRLV1CG>: ahh thank you! Makes a lot of sense :relieved:",
        "ts": "1470957556.000269",
        "reactions": [
            {
                "name": "slightly_smiling_face",
                "users": [
                    "U1KRLV1CG"
                ],
                "count": 1
            }
        ]
    },
    {
        "type": "message",
        "user": "U1KR9BP0E",
        "text": "This is a great question for practice if anyone hasn't done it yet. Kind of a unique situation like we covered in review today.\n\n21.The following SAS program is submitted:\ndata work.AreaCodes;\nPhonenumber=3125551212;\nCode='('!!substr(Phonenumber,1,3)!!')';\nrun;\nWhich one of the following is the value of the variable Code in the output data set?\na. ( 3)\nb. (312)\nc. 3\nd. 312\n\nCorrect answer: a",
        "ts": "1470957866.000270"
    },
    {
        "type": "message",
        "user": "U1KR9BP0E",
        "text": "option a is actually (  3) with two spaces between the ( and the 3",
        "ts": "1470957890.000271"
    },
    {
        "type": "message",
        "user": "U1KR9BP0E",
        "text": "Explanation:\nAn automatic data conversion is performed whenever a numeric variable is used where\nSAS expects a character value. The numeric variable is written with the BEST12. format\nand the resulting character value is right-aligned when the conversion occurs. In this\nexample, the value of Phonenumber is converted to character and right-aligned before the\nSUBSTR function is performed. Since there are only 10 digits in the value of\nPhonenumber, the right-aligned value begins with two blanks. Therefore the SUBSTR\nfunction picks up two blanks and a 3, and uses the BEST12. format to assign that value to\nCode. Then, the parentheses are concatenated before and after the two blanks and a 3.",
        "ts": "1470957911.000272",
        "reactions": [
            {
                "name": "+1::skin-tone-5",
                "users": [
                    "U1KQYG6SJ",
                    "U1KSR4JP3",
                    "U1KSYP1M5"
                ],
                "count": 3
            },
            {
                "name": "neutral_face",
                "users": [
                    "U1P8QBBD1"
                ],
                "count": 1
            }
        ]
    },
    {
        "type": "message",
        "user": "U1KRSV7AN",
        "text": "That's a dirty one, <@U1KR9BP0E>  I think SAS test makers sit around high-fiving each other every time they come up with a tricky question. ",
        "ts": "1470959015.000273",
        "reactions": [
            {
                "name": "joy",
                "users": [
                    "U1NUU2U9E",
                    "U1KR9BP0E",
                    "U1KRLV1CG",
                    "U1LBRCSEA",
                    "U1KRE1L9M",
                    "U1P8QBBD1",
                    "U1KT9ATA5"
                ],
                "count": 7
            },
            {
                "name": "+1",
                "users": [
                    "U1KSYP1M5",
                    "U1KT2JJE8"
                ],
                "count": 2
            }
        ]
    },
    {
        "type": "message",
        "user": "U1NUU2U9E",
        "text": "so i thought we can't change the length of a variable after it is created...",
        "ts": "1470959114.000275"
    },
    {
        "type": "message",
        "user": "U1NUU2U9E",
        "text": "help please?",
        "ts": "1470959122.000276"
    },
    {
        "type": "message",
        "user": "U1NUU2U9E",
        "text": "i understand that it is spoken about format... but the length???",
        "ts": "1470959162.000277"
    },
    {
        "type": "message",
        "user": "U1KRSV7AN",
        "text": "The question refers to the format, not the length.",
        "ts": "1470959163.000278"
    },
    {
        "type": "message",
        "user": "U1KRSV7AN",
        "text": "It's tricky.",
        "ts": "1470959167.000279"
    },
    {
        "type": "message",
        "user": "U1L9DD1NY",
        "text": "It's asking for formats ",
        "ts": "1470959167.000280"
    },
    {
        "type": "message",
        "user": "U1L9DD1NY",
        "text": "Not the length !!",
        "ts": "1470959172.000281"
    },
    {
        "type": "message",
        "user": "U1L9DD1NY",
        "text": "^^",
        "ts": "1470959174.000282"
    },
    {
        "type": "message",
        "user": "U1L9DD1NY",
        "text": "Yea what he said ",
        "ts": "1470959177.000283"
    },
    {
        "type": "message",
        "user": "U1NUU2U9E",
        "text": "ok... and what is the difference between  $20 and $CHAR20 then?",
        "ts": "1470959238.000284"
    },
    {
        "type": "message",
        "user": "U1NUU2U9E",
        "text": "just as an example",
        "ts": "1470959245.000285"
    },
    {
        "type": "message",
        "user": "U1KRLV1CG",
        "text": "We can't after it is created. this is true. In this case, we are changing it before it is created. The length statement is placed before the merge statement. Be aware of the difference between a length and a format though",
        "ts": "1470959254.000286"
    },
    {
        "type": "message",
        "user": "U1KR9BP0E",
        "text": "if its a merge, format in the new dataset takes the same value as that variable in the first dataset in the merge statement (in this case, in sales)",
        "ts": "1470959256.000287"
    },
    {
        "type": "message",
        "user": "U1NUU2U9E",
        "text": "both are chars, right?",
        "ts": "1470959259.000288"
    },
    {
        "type": "message",
        "user": "U1KRSV7AN",
        "text": "$20 is the maximum length of the variable in the data set. $CHAR20 is the format with which the variable will be DISPLAYED",
        "ts": "1470959291.000289",
        "reactions": [
            {
                "name": "+1",
                "users": [
                    "U1KRLV1CG",
                    "U1KT2JJE8"
                ],
                "count": 2
            }
        ]
    },
    {
        "type": "message",
        "user": "U1NUU2U9E",
        "text": "struggling with the notions of format and length...",
        "ts": "1470959298.000290",
        "reactions": [
            {
                "name": "+1",
                "users": [
                    "U1KRLV1CG"
                ],
                "count": 1
            }
        ]
    },
    {
        "type": "message",
        "user": "U1KRSV7AN",
        "text": "Format is for display. Length is for actual byte allocation in the data set.",
        "ts": "1470959321.000292",
        "reactions": [
            {
                "name": "+1",
                "users": [
                    "U1KRLV1CG",
                    "U1KR9BP0E",
                    "U1L9DD1NY"
                ],
                "count": 3
            }
        ]
    },
    {
        "type": "message",
        "user": "U1L1D4WG7",
        "text": "$20 goes with length. $char20 is a format.",
        "ts": "1470959328.000293"
    },
    {
        "type": "message",
        "user": "U1KR9BP0E",
        "text": "<@U1L9DD1NY> yes, I believe so",
        "ts": "1470959361.000294"
    },
    {
        "type": "message",
        "user": "U1KRLV1CG",
        "text": "Yes <@U1L9DD1NY>",
        "ts": "1470959362.000295"
    },
    {
        "type": "message",
        "user": "U1L9DD1NY",
        "text": "Okay thanks!!! ",
        "ts": "1470959366.000296"
    },
    {
        "type": "message",
        "user": "U1L1D4WG7",
        "text": "Yea... What <@U1KRSV7AN> said that I finally saw lol\n",
        "ts": "1470959371.000297",
        "reactions": [
            {
                "name": "+1",
                "users": [
                    "U1KRSV7AN",
                    "U1NUU2U9E",
                    "U1KRLV1CG"
                ],
                "count": 3
            }
        ]
    },
    {
        "type": "message",
        "user": "U1NUU2U9E",
        "text": "Thanks everyone!",
        "ts": "1470959397.000298"
    },
    {
        "type": "message",
        "user": "U1KT2JJE8",
        "text": " Yes, you are right. \"Rename jcode to jobcode\" is how I read it to myself to remember.",
        "ts": "1470959747.000300"
    },
    {
        "type": "message",
        "user": "U1L9DD1NY",
        "text": "So written the other way around jobcode and Jcode would be written to the output dataset?",
        "ts": "1470959837.000301"
    },
    {
        "type": "message",
        "user": "U1KT2JJE8",
        "text": "Meaning what in terms of code?",
        "ts": "1470959902.000302"
    },
    {
        "type": "message",
        "user": "U1L9DD1NY",
        "text": "If it was rename = jobcode = Jcode ",
        "ts": "1470959976.000303"
    },
    {
        "type": "message",
        "user": "U1L9DD1NY",
        "text": "I think I'm confusing myself ",
        "ts": "1470960021.000304"
    },
    {
        "type": "message",
        "user": "U1KT2JJE8",
        "text": "Jobcode isn't currently a variable in dept2 so you can't. ",
        "ts": "1470960023.000305",
        "reactions": [
            {
                "name": "+1",
                "users": [
                    "U1KRLV1CG"
                ],
                "count": 1
            }
        ]
    },
    {
        "type": "message",
        "user": "U1L9DD1NY",
        "text": "Oo okay nvm I was thinking about it the wrong way haha thanks ",
        "ts": "1470960037.000306"
    },
    {
        "type": "message",
        "user": "U1KT2JJE8",
        "text": "You could do it for dept1 in which case only jcode would be written out",
        "ts": "1470960060.000307"
    },
    {
        "type": "message",
        "user": "U1NUU2U9E",
        "text": "how would those of us who took the exam compare the practice exam to the real one?",
        "ts": "1470960077.000308"
    },
    {
        "type": "message",
        "user": "U1KRLV1CG",
        "text": "I thought the real exam was easier. I got 68% on the practice exam, which stressed the hell out of me and 97% on the real one. Day and night. You will all be fine :slightly_smiling_face:",
        "ts": "1470960176.000309",
        "reactions": [
            {
                "name": "fire",
                "users": [
                    "U1KR9BP0E",
                    "U1KRE1L9M",
                    "U1KSR4JP3",
                    "U1KRB11QC",
                    "U1NDG6ULB",
                    "U1LAAMJ0M",
                    "U1KSL7C10",
                    "U1L6YQUSU"
                ],
                "count": 8
            }
        ]
    },
    {
        "type": "message",
        "user": "U1L9DD1NY",
        "text": "Wow that makes me feel a lot better <@U1KRLV1CG> ",
        "ts": "1470960200.000310",
        "reactions": [
            {
                "name": "slightly_smiling_face",
                "users": [
                    "U1KRLV1CG",
                    "U1P8QBBD1",
                    "U1LAAMJ0M"
                ],
                "count": 3
            }
        ]
    },
    {
        "type": "message",
        "user": "U1KR9BP0E",
        "text": "thanks SO much to everyone from the first batch who has been going out of their way to help us today - you are angels!",
        "ts": "1470960250.000311",
        "reactions": [
            {
                "name": "+1",
                "users": [
                    "U1NUU2U9E",
                    "U1L9DD1NY",
                    "U1KT2JJE8",
                    "U1LJRDPLP",
                    "U1KRE5NKZ",
                    "U1LBRCSEA",
                    "U1MBURU4D",
                    "U1KT3UELS",
                    "U1KSR4JP3",
                    "U1KRB11QC",
                    "U1P8QBBD1",
                    "U1SMADBU4"
                ],
                "count": 12
            },
            {
                "name": "slightly_smiling_face",
                "users": [
                    "U1KRLV1CG"
                ],
                "count": 1
            },
            {
                "name": "raised_hands",
                "users": [
                    "U1NDG6ULB"
                ],
                "count": 1
            }
        ]
    },
    {
        "type": "message",
        "user": "U1NUU2U9E",
        "text": "<@U1KRLV1CG>: thanks for the perspective :smile:",
        "ts": "1470960251.000312",
        "reactions": [
            {
                "name": "slightly_smiling_face",
                "users": [
                    "U1KRLV1CG",
                    "U1KT2JJE8",
                    "U1KRB11QC"
                ],
                "count": 3
            }
        ]
    },
    {
        "type": "message",
        "user": "U1L9DD1NY",
        "text": "Yes thank you guys so much! ",
        "ts": "1470960293.000313"
    },
    {
        "type": "message",
        "user": "U1KRSV7AN",
        "text": "I just tested it with another data set and it didn't break.",
        "ts": "1470961507.000315",
        "reactions": [
            {
                "name": "+1",
                "users": [
                    "U1KRLV1CG"
                ],
                "count": 1
            }
        ]
    },
    {
        "type": "message",
        "user": "U1KRSV7AN",
        "text": "proc sort data = sashelp.cars out = tempcars;\n\tby type;\nrun;\n\nproc print data = tempcars;\n\tvar type origin drivetrain;\n\tby type;\nrun;",
        "ts": "1470961514.000316"
    },
    {
        "type": "message",
        "user": "U1KRSV7AN",
        "text": "The code above should work for you, too.",
        "ts": "1470961524.000317"
    },
    {
        "type": "message",
        "user": "U1KT2JJE8",
        "text": "What if we switch the sum and the where, will it include values in the sum that get subsetted out?",
        "ts": "1470961716.000318"
    },
    {
        "type": "message",
        "user": "U1KRLV1CG",
        "text": "nope. The Where statement is the first one that is read independently of where (no pun intended) it is placed in the program",
        "ts": "1470961805.000319",
        "reactions": [
            {
                "name": "joy",
                "users": [
                    "U1KRWUXFU"
                ],
                "count": 1
            }
        ]
    },
    {
        "type": "message",
        "user": "U1KRSV7AN",
        "text": "Yeah, I believe that will change the code.",
        "ts": "1470961809.000320"
    },
    {
        "type": "message",
        "user": "U1KRLV1CG",
        "text": "disagreement! haha",
        "ts": "1470961824.000321"
    },
    {
        "type": "message",
        "user": "U1KRSV7AN",
        "text": "Haha, no, sorry, I think I'm agreeing and not saying it right! The where subsets at the where, correct?",
        "ts": "1470961841.000322"
    },
    {
        "type": "message",
        "user": "U1KRSV7AN",
        "text": "As in, once the it reads the where statement, it filters out anything that doesn't meet the condition.",
        "ts": "1470961875.000323"
    },
    {
        "type": "message",
        "user": "U1KRLV1CG",
        "text": "Consensus :slightly_smiling_face:",
        "ts": "1470961946.000324"
    },
    {
        "type": "message",
        "user": "U1KRSV7AN",
        "text": ":slightly_smiling_face:",
        "ts": "1470961950.000325"
    },
    {
        "type": "message",
        "user": "U1KRSV7AN",
        "text": "<@U1KT2JJE8>: did any of that make sense?",
        "ts": "1470961968.000326"
    },
    {
        "type": "message",
        "user": "U1KT2JJE8",
        "text": "Well, I just tested it and you get the same result if the sum is before the where and if you reverse them.",
        "ts": "1470962113.000327"
    },
    {
        "type": "message",
        "user": "U1KRSV7AN",
        "text": "Ah, I think I know what's going on. It's summing whatever values are being subsetted. I think I was misunderstanding what sum was doing in this case.",
        "ts": "1470962377.000328"
    },
    {
        "user": "U1Q7LP4V9",
        "text": "<@U1Q7LP4V9|jestover> has joined the channel",
        "type": "message",
        "subtype": "channel_join",
        "ts": "1470962406.000329"
    },
    {
        "user": "U1LAAMJ0M",
        "text": "<@U1LAAMJ0M|carlanderson> has joined the channel",
        "type": "message",
        "subtype": "channel_join",
        "ts": "1470962443.000330"
    },
    {
        "type": "message",
        "user": "U1KRSV7AN",
        "text": "Hey all, curious if y'all know why this is D. I think it's because SAS automatically uses the space as a delimiter, but I wanted to confirm:\n\n59.Given the contents of the raw data file TYPECOLOR.DAT: \n \n  ----+----10---+----20---+----30\n  daisyyellow\n \nThe following SAS program is submitted:\n \n  data FLOWERS;\n     infile 'TYPECOLOR.DAT' truncover;\n     length\n        Type $ 5\n        Color $ 11;\n     input \n        Type $ \n        Color $;\n  run;\n \nWhat are the values of the variables Type and Color?\n\n     A. Type=daisy, Color=yellow \n     B. Type=daisy, Color=w\n     C. Type=daisy, Color=daisyyellow\n     D. Type=daisy, Color=\n\nAnswer: D",
        "ts": "1470962477.000331"
    },
    {
        "type": "message",
        "user": "U1L9DD1NY",
        "text": "Side note about this question what is the truncover option there for ",
        "ts": "1470962573.000332"
    },
    {
        "type": "message",
        "user": "U1L1D4WG7",
        "text": "I think there is no space in the data, so it skips ahead.",
        "ts": "1470962576.000333"
    },
    {
        "type": "message",
        "user": "U1L1D4WG7",
        "text": "Haven't tested this one...",
        "ts": "1470962636.000334"
    },
    {
        "type": "message",
        "user": "U1KRLV1CG",
        "text": "Yes the default space delimiter is doing it all. As for the truncover <@U1L9DD1NY> I had to google it when I run into this question and SAS help was not too helpful. I don't think it is related to the point of the question though",
        "ts": "1470962661.000335"
    },
    {
        "type": "message",
        "user": "U1KRSV7AN",
        "text": "<@U1L1D4WG7>: that's what I was thinking.",
        "ts": "1470962662.000336"
    },
    {
        "type": "message",
        "user": "U1L1D4WG7",
        "text": "If there was a space, the truncover would allow it to load the word yellow, even though it isn't 11 chars long.",
        "ts": "1470962739.000337",
        "reactions": [
            {
                "name": "+1",
                "users": [
                    "U1KRLV1CG",
                    "U1KRSV7AN"
                ],
                "count": 2
            }
        ]
    },
    {
        "type": "message",
        "user": "U1KRSV7AN",
        "text": "<@U1L9DD1NY>: \n\ntruncover:\n Forces the INPUT\nstatement to stop\nreading when it gets to\nthe end of a short line.\nThis option will not\nskip information.",
        "ts": "1470962745.000338"
    },
    {
        "type": "message",
        "user": "U1KRSV7AN",
        "text": "As opposed to missover:\n\nSets all empty vars to\nmissing when reading a\nshort line. However, it\ncan also skip values.",
        "ts": "1470962756.000339"
    },
    {
        "type": "message",
        "user": "U1KRLV1CG",
        "text": "<@U1L1D4WG7>:  Now the SAS explanation makes sense :slightly_smiling_face:",
        "ts": "1470962807.000340"
    },
    {
        "type": "message",
        "user": "U1NDG6ULB",
        "text": "<@U1L9DD1NY>: This helped me understand the different options as well as the defaut 'flowover' option mentioned before <http:\/\/www2.sas.com\/proceedings\/sugi26\/p009-26.pdf>",
        "ts": "1470962899.000341"
    },
    {
        "type": "message",
        "user": "U1KRSV7AN",
        "text": "<@U1L1D4WG7>: so, without truncover, and if there was a space, would yellow not load because it's not 11 characters?",
        "ts": "1470962910.000342"
    },
    {
        "type": "message",
        "user": "U1KRSV7AN",
        "text": "Wouldn't it still load?",
        "ts": "1470962943.000343"
    },
    {
        "type": "message",
        "user": "U1L1D4WG7",
        "text": "Not sure. I think maybe not, but the behavior can be different for list vs formatted input mode, so it should be tested to be sure. I don't have SAS handy at the moment :-(",
        "ts": "1470963225.000344"
    },
    {
        "type": "message",
        "user": "U1L9DD1NY",
        "text": "Okay thank you!",
        "ts": "1470963330.000345"
    },
    {
        "type": "message",
        "user": "U1NDG6ULB",
        "text": "What does the '?' operator do?",
        "ts": "1470963539.000346"
    },
    {
        "type": "message",
        "user": "U1L6WB44A",
        "text": "I think it's the symbol for 'contains'",
        "ts": "1470963573.000347"
    },
    {
        "type": "message",
        "user": "U1L6WB44A",
        "text": "(Makes total sense)",
        "ts": "1470963594.000348",
        "reactions": [
            {
                "name": "grinning",
                "users": [
                    "U1KRLV1CG"
                ],
                "count": 1
            }
        ]
    },
    {
        "type": "message",
        "user": "U1NDG6ULB",
        "text": "Ahhh thanks. Yep thats definitely it <http:\/\/www2.sas.com\/proceedings\/sugi26\/p009-26.pdf>",
        "ts": "1470963689.000349"
    },
    {
        "type": "message",
        "user": "U1KQYG6SJ",
        "text": "at this point, when I see that sign, I say in my head (is it there) instead of trying to read the sentence with a ? :smile:",
        "ts": "1470963715.000350"
    },
    {
        "type": "message",
        "user": "U1KR9BP0E",
        "text": "<@U1L6WB44A>: I don't think it's contains, because I got this wrong:",
        "ts": "1470963830.000351"
    },
    {
        "type": "message",
        "user": "U1KR9BP0E",
        "text": "20.  \nThe SAS data set Employees is listed below.\n\nEmployees\nName\tSalary\nPatel\t160000\nPayne\t50000\nEllis\t55000\nLiu\t45000\n\n\nThe following SAS program is submitted:\nproc print data=employees;\n   where name ? E;\nrun;\nWhat is the result?\na.\tNo observations are written to the report.\nb.\tThe observation for Ellis only is written to the report.\nc.\tThe observations for Patel and Payne only are written to the report.\nd.\tThe observations for Patel, Payne, and Ellis only are written to the report.\nCorrect answer:   a\n\nYour answer:  d\n\nThe WHERE statement involves a variable named E, which does not exist in the Work.Employees data set. This is a syntax error so no observations are written.    Return to top",
        "ts": "1470963831.000352"
    },
    {
        "type": "message",
        "user": "U1KQYG6SJ",
        "text": "I think you need ' '",
        "ts": "1470963849.000353",
        "reactions": [
            {
                "name": "+1",
                "users": [
                    "U1L6WB44A",
                    "U1KRLV1CG",
                    "U1KRWUXFU",
                    "U1KRE1L9M",
                    "U1L6YQUSU"
                ],
                "count": 5
            }
        ]
    },
    {
        "type": "message",
        "user": "U1KQYG6SJ",
        "text": "to check for it, else it's a variable name",
        "ts": "1470963855.000354"
    },
    {
        "type": "message",
        "user": "U1KR9BP0E",
        "text": "OH yes, good catch. So ? is contains.",
        "ts": "1470963867.000355"
    },
    {
        "type": "message",
        "user": "U1KRWUXFU",
        "text": "<@U1KQYG6SJ> I agree! ",
        "ts": "1470963868.000356"
    },
    {
        "type": "message",
        "user": "U1KR9BP0E",
        "text": "thanks so much",
        "ts": "1470963869.000357"
    },
    {
        "type": "message",
        "user": "U1KQYG6SJ",
        "text": "also, keep in mind that it'll be case sensitive",
        "ts": "1470963890.000358",
        "reactions": [
            {
                "name": "+1",
                "users": [
                    "U1L6WB44A",
                    "U1NDG6ULB"
                ],
                "count": 2
            }
        ]
    },
    {
        "type": "message",
        "user": "U1KR9BP0E",
        "text": "Am I reading this wrong over and over? If I do as the answer says and put \"It\" between \"Is\" and \"Blue\", isn't it \"IsItBlue\"?\n\nThe following SAS program is submitted:  \ndata work.words;\n   word1='Is';\n   word2='It';\n   word3='Blue';\n   all=catx(word1,word2,word3);\nrun;\nThe variable All is created with which value? Note that the quotes are shown for readability and are not part of the value.\na.\t\"It Is Blue\"\nb.\t\"ItIsBlue\"\nc.\t\"It      Is    Blue\"\nd.\t\"IsItBlue\"\nCorrect answer:   b\n\nYour answer:  d\n\nIn the CATX function, the first argument is the delimiter that is used when the other arguments are put together. So, we are putting It together with Blue and have Is as the delimiter between them.    Return to top",
        "ts": "1470964101.000359"
    },
    {
        "type": "message",
        "user": "U1KR9BP0E",
        "text": "Yes, yes I was reading it wrong over and over.",
        "ts": "1470964152.000360"
    },
    {
        "type": "message",
        "user": "U1KR9BP0E",
        "text": "Hope that helps someone else at least, for making myself look like I can't read...",
        "ts": "1470964198.000361",
        "reactions": [
            {
                "name": "joy",
                "users": [
                    "U1KRLV1CG",
                    "U1KRWUXFU"
                ],
                "count": 2
            }
        ]
    },
    {
        "type": "message",
        "user": "U1KQYG6SJ",
        "text": ":joy:",
        "ts": "1470964230.000362"
    },
    {
        "type": "message",
        "user": "U1KQYG6SJ",
        "text": "maybe you should take a nap",
        "ts": "1470964235.000363"
    },
    {
        "type": "message",
        "user": "U1KQYG6SJ",
        "text": "especially if you find yourself doing this multiple times:",
        "ts": "1470964254.000364"
    },
    {
        "type": "message",
        "user": "U1KQYG6SJ",
        "text": "\/giphy nerd rage",
        "edited": {
            "user": "U1KQYG6SJ",
            "ts": "1470964321.000000"
        },
        "ts": "1470964258.000365"
    },
    {
        "type": "message",
        "user": "U1KQYG6SJ",
        "text": "wrong gif",
        "ts": "1470964262.000366"
    },
    {
        "type": "message",
        "user": "U1KQYG6SJ",
        "text": "<http:\/\/giphy.com\/gifs\/cravetvcanada-30-rock-cravetv-l2QZWG9KvAs6zx4iI>",
        "attachments": [
            {
                "service_name": "Giphy",
                "service_url": "http:\/\/giphy.com\/",
                "image_url": "http:\/\/media1.giphy.com\/media\/l2QZWG9KvAs6zx4iI\/giphy.gif",
                "image_width": 666,
                "image_height": 372,
                "image_bytes": 2832688,
                "fallback": "giphy: http:\/\/giphy.com\/gifs\/cravetvcanada-30-rock-cravetv-l2QZWG9KvAs6zx4iI",
                "service_icon": "https:\/\/a.slack-edge.com\/2089\/img\/unfurl_icons\/giphy.png",
                "id": 1
            }
        ],
        "ts": "1470964303.000369"
    },
    {
        "user": "U1L90S3QC",
        "text": "<@U1L90S3QC|cwstjeor> has joined the channel",
        "type": "message",
        "subtype": "channel_join",
        "ts": "1470964902.000372"
    },
    {
        "type": "message",
        "user": "U1KQYG6SJ",
        "text": "you should probably see if you have any updates and run them tonight, or check the time that your updates run and make sure it's not during the test time. Also, probably a good idea to do a restart tomorrow morning to clear \"gunk\" out\/free up resources that are being hoarded and get a clean slate.",
        "edited": {
            "user": "U1KQYG6SJ",
            "ts": "1470966308.000000"
        },
        "ts": "1470966295.000373",
        "reactions": [
            {
                "name": "+1",
                "users": [
                    "U1KRWUXFU",
                    "U1KT2JJE8"
                ],
                "count": 2
            }
        ]
    },
    {
        "type": "message",
        "user": "U1L6YQUSU",
        "text": "Just checking in and reading the 200 posts.  Looks like <@U1KRLV1CG> is keeping you guys straight.  :sunglasses:",
        "ts": "1470967582.000375",
        "reactions": [
            {
                "name": "slightly_smiling_face",
                "users": [
                    "U1KRLV1CG",
                    "U1KRB11QC",
                    "U1NUU2U9E"
                ],
                "count": 3
            }
        ]
    },
    {
        "type": "message",
        "user": "U1L6YQUSU",
        "text": "But the test is way easier than these blog posts.  You're all going to do an amazing job.",
        "ts": "1470967745.000376"
    },
    {
        "type": "message",
        "user": "U1KQYG6SJ",
        "text": "I will hold you to that statement <@U1L6YQUSU>",
        "ts": "1470967954.000377"
    },
    {
        "type": "message",
        "user": "U1KRLV1CG",
        "text": "I second that <@U1L6YQUSU>. It looks like the blog posts are there to stretch us, but don't let them destroy your morale like they did to me.",
        "ts": "1470968288.000378"
    },
    {
        "type": "message",
        "user": "U1KQ9523D",
        "text": "I agree with <@U1L6YQUSU> and <@U1KRLV1CG> , the real test is no where near as hard as the practice! If you guys went through the blog\/practice tests then you are well prepared for any tricky question they could throw at you and there weren't many!! You will all do amazing :slightly_smiling_face:",
        "edited": {
            "user": "U1KQ9523D",
            "ts": "1470968324.000000"
        },
        "ts": "1470968312.000379",
        "reactions": [
            {
                "name": "pray",
                "users": [
                    "U1KSL7C10"
                ],
                "count": 1
            }
        ]
    },
    {
        "type": "message",
        "user": "U1KRLV1CG",
        "text": "Also, a few blog posts appeared slightly altered, so the answer was different. Don't memorize answers, understand the logic. YOU WILL ALL PASS:muscle:",
        "ts": "1470968385.000381",
        "reactions": [
            {
                "name": "hugging_face",
                "users": [
                    "U1L9DD1NY"
                ],
                "count": 1
            }
        ]
    },
    {
        "type": "message",
        "user": "U1L9DD1NY",
        "text": "I'm having a lot of trouble with arrays. Could someone explain to me why the answer is C?",
        "ts": "1470968486.000382"
    },
    {
        "type": "message",
        "user": "U1KRLV1CG",
        "text": "The key word is \"New.\" They want to see which variables are created through an array that were NOT in the data set already",
        "ts": "1470968552.000384"
    },
    {
        "type": "message",
        "user": "U1L9DD1NY",
        "text": "Yes but why are those the new ones lol ",
        "ts": "1470968619.000385"
    },
    {
        "type": "message",
        "user": "U1KRLV1CG",
        "text": "so we have jansales febsales and marsales that already exist in the dataset as you can see in the keep option in the beginning. Those are assigned to the seccond array",
        "ts": "1470968624.000386",
        "reactions": [
            {
                "name": "+1::skin-tone-5",
                "users": [
                    "U1KQYG6SJ"
                ],
                "count": 1
            }
        ]
    },
    {
        "type": "message",
        "user": "U1L9DD1NY",
        "text": "OHH okay ",
        "ts": "1470968631.000387"
    },
    {
        "type": "message",
        "user": "U1KRLV1CG",
        "text": "the first array just creates variables",
        "ts": "1470968634.000388"
    },
    {
        "type": "message",
        "user": "U1L9DD1NY",
        "text": "I looked over the keep thing thank u",
        "ts": "1470968638.000389",
        "reactions": [
            {
                "name": "slightly_smiling_face",
                "users": [
                    "U1KRLV1CG"
                ],
                "count": 1
            }
        ]
    },
    {
        "type": "message",
        "user": "U1L9DD1NY",
        "text": "Question. If it was just array diff_sales(3) would the new variables be diff_sales1 etc ",
        "ts": "1470968713.000390"
    },
    {
        "type": "message",
        "user": "U1L6YQUSU",
        "text": "Yes, <@U1L9DD1NY> ",
        "ts": "1470968794.000391",
        "reactions": [
            {
                "name": "+1",
                "users": [
                    "U1KRLV1CG"
                ],
                "count": 1
            }
        ]
    },
    {
        "type": "message",
        "user": "U1L6YQUSU",
        "text": "It's not reading.  It's writing. ",
        "ts": "1470968862.000393"
    },
    {
        "type": "message",
        "user": "U1L6YQUSU",
        "text": "You're using a \"put\" statement to create a file, not \"input\" to read a file.  ",
        "ts": "1470968883.000394"
    },
    {
        "type": "message",
        "user": "U1L6YQUSU",
        "text": "So the directions are telling SAS where to write the variables on each line. ",
        "ts": "1470968900.000395"
    },
    {
        "type": "message",
        "user": "U1L6YQUSU",
        "text": " It puts the name first and then writes the age starting in column 5",
        "ts": "1470968922.000396",
        "reactions": [
            {
                "name": "+1",
                "users": [
                    "U1KRLV1CG",
                    "U1KSYP1M5",
                    "U1L9DD1NY"
                ],
                "count": 3
            }
        ]
    },
    {
        "type": "message",
        "user": "U1KSYP1M5",
        "text": "Ahhhh thank you <@U1L6YQUSU> the lightbulb just came on, I see now thank you! :information_desk_person::skin-tone-4: ",
        "ts": "1470968958.000397",
        "reactions": [
            {
                "name": "nerd_face",
                "users": [
                    "U1L6YQUSU",
                    "U1L9DD1NY"
                ],
                "count": 2
            }
        ]
    },
    {
        "type": "message",
        "user": "U1L9DD1NY",
        "text": "Why is that one 3 again?! ",
        "ts": "1470970865.000398"
    },
    {
        "type": "message",
        "user": "U1KRLV1CG",
        "text": "age will all be missing. Missing values are the smallest values SAS can have so less than 10",
        "ts": "1470970995.000400"
    },
    {
        "type": "message",
        "user": "U1LAAMJ0M",
        "text": "Age is input as a missing value because it is trying to read the last name as a numeric",
        "ts": "1470971040.000401",
        "reactions": [
            {
                "name": "+1",
                "users": [
                    "U1KRLV1CG"
                ],
                "count": 1
            }
        ]
    },
    {
        "type": "message",
        "user": "U1L9DD1NY",
        "text": "Is it cause the length isn't specified ",
        "ts": "1470971041.000402"
    },
    {
        "type": "message",
        "user": "U1L9DD1NY",
        "text": "Oh ",
        "ts": "1470971046.000403"
    },
    {
        "type": "message",
        "user": "U1L9DD1NY",
        "text": "Nvm ",
        "ts": "1470971047.000404"
    },
    {
        "type": "message",
        "user": "U1L9DD1NY",
        "text": "Okay!",
        "ts": "1470971049.000405"
    },
    {
        "type": "message",
        "user": "U1LAAMJ0M",
        "text": "Why is the length of referen 17 here?",
        "ts": "1470972659.000407"
    },
    {
        "type": "message",
        "user": "U1KQ9523D",
        "text": "When SAS converts the numeric to character it uses the best12. format that the prod is stored as. So you have a length of 4 for item, and 12 for prod, and 1 for the '\/'",
        "edited": {
            "user": "U1KQ9523D",
            "ts": "1470973629.000000"
        },
        "ts": "1470972784.000408"
    },
    {
        "type": "message",
        "user": "U1LAAMJ0M",
        "text": "Oh man, thanks",
        "ts": "1470972859.000409",
        "reactions": [
            {
                "name": "+1",
                "users": [
                    "U1KQ9523D"
                ],
                "count": 1
            }
        ]
    },
    {
        "user": "U1KRTU0UQ",
        "text": "<@U1KRTU0UQ|catherinebarnes> has joined the channel",
        "type": "message",
        "subtype": "channel_join",
        "ts": "1470980861.000411"
    }
]