[
    {
        "user": "U1KT2JJE8",
        "type": "message",
        "subtype": "channel_join",
        "text": "<@U1KT2JJE8|slwalke3> has joined the channel",
        "ts": "1467465271.000013"
    },
    {
        "type": "message",
        "user": "U1L914KNJ",
        "text": "are there any chapters not spoken for? I'm in to help!",
        "ts": "1467479625.000014"
    },
    {
        "type": "message",
        "user": "U1KRB11QC",
        "text": "10-11 still need to be tackled ",
        "ts": "1467481293.000015"
    },
    {
        "type": "message",
        "user": "U1L914KNJ",
        "text": "Great! I'll do 10-11. Thanks <@U1KRB11QC>",
        "ts": "1467481569.000016"
    },
    {
        "type": "message",
        "user": "U1KRB11QC",
        "text": "I'll set up a link so you can add questions and will post it to the forum",
        "ts": "1467481683.000017"
    },
    {
        "type": "message",
        "user": "U1KRE1L9M",
        "text": "Test for chapters 4-5 is now complete! I'd appreciate if someone would take it to see if there are any errors",
        "ts": "1467491136.000018"
    },
    {
        "type": "message",
        "user": "U1L6YQUSU",
        "text": "Check the forum for a couple of general posts from me, one for your quiz <@U1KRE1L9M> ",
        "ts": "1467493251.000019"
    },
    {
        "user": "U1L9669PD",
        "type": "message",
        "subtype": "channel_join",
        "text": "<@U1L9669PD|pmartin> has joined the channel",
        "ts": "1467493500.000020"
    },
    {
        "user": "U1L1D4UG6",
        "type": "message",
        "subtype": "channel_join",
        "text": "<@U1L1D4UG6|laurahc55> has joined the channel",
        "ts": "1467513131.000021"
    }
]